rsb_git/__init__.py
rsb_git/_git.py
rsb_git/_version.py
rsb_osa_generator-0.0.1.dist-info/LICENSE
rsb_osa_generator-0.0.1.dist-info/METADATA
rsb_osa_generator-0.0.1.dist-info/WHEEL
rsb_osa_generator-0.0.1.dist-info/top_level.txt
rsb_osa_generator-0.0.1.dist-info/RECORD
